4-bit-wallace/4bitwallace.v
module half_adder(
    Data_in_A,
    Data_in_B,
    Data_out_Sum,
    Data_out_Carry
    );

    //what are the input ports.
    input Data_in_A;
    input Data_in_B;
    //What are the output ports.
    output Data_out_Sum;
     output Data_out_Carry;
     
     //Implement the Sum and Carry equations using Verilog Bit operators.
     assign Data_out_Sum = Data_in_A ^ Data_in_B;  //XOR operation
     assign Data_out_Carry = Data_in_A & Data_in_B; //AND operation
    
endmodule

module full_adder(
    Data_in_A,  //input A
    Data_in_B,  //input B
    Data_in_C,  //input C
     Data_out_Sum,
     Data_out_Carry
    );

    //what are the input ports.
    input Data_in_A;
    input Data_in_B;
     input Data_in_C;
    //What are the output ports.
    output Data_out_Sum;
     output Data_out_Carry;
     //Internal variables
     wire ha1_sum;
     wire ha2_sum;
     wire ha1_carry;
     wire ha2_carry;
     wire Data_out_Sum;
     wire Data_out_Carry;

     //Instantiate the half adder 1
    half_adder  ha1(
        .Data_in_A(Data_in_A),
        .Data_in_B(Data_in_B),
        .Data_out_Sum(ha1_sum),
        .Data_out_Carry(ha1_carry)
    );
    
    //Instantiate the half adder 2
    half_adder  ha2(
        .Data_in_A(Data_in_C),
        .Data_in_B(ha1_sum),
        .Data_out_Sum(ha2_sum),
        .Data_out_Carry(ha2_carry)
    );

    //sum output from 2nd half adder is connected to full adder output
    assign Data_out_Sum = ha2_sum;  
    //The carry's from both the half adders are OR'ed to get the final carry./
    assign Data_out_Carry = ha1_carry | ha2_carry;
    
endmodule

module fourbitwallace(aIn, bIn, compProd, ovf);
    input [3:0] aIn, bIn;
    output [7:0] compProd;
    output ovf;

    wire twosComp;
    assign twosComp = aIn[3] ^ bIn[3];

    wire [3:0] a, b;
    assign a = aIn[3] ? (~aIn) + 1 : aIn; // 2s comp A to positive
    assign b = bIn[3] ? (~bIn) + 1 : bIn; // 2s comp B to positive

    // if toggle flag = 1 then twos comp product
    wire [7:0] p;
    assign compProd = twosComp ? (~p) + 1 : p;

    wire allones, allzeros, high_bits, msb_match;
	assign allones = & p[7:4];
	assign allzeros = | p[7:4];
	assign high_bits = allones ^ allzeros; //ovf = 1 if !allzeros and !allones
	assign msb_match = allzeros ^ p[3];
	assign ovf = high_bits & msb_match;

    wire Cout;

    // 4 levels of horiz. cout lines
    wire [4:0] c1;
    wire [4:0] c2;
    wire [4:0] c3;
    wire [4:0] c4;

    assign c1[0] = 1'b0;
    assign c2[0] = 1'b0;
    assign c3[0] = 1'b0;
    assign c4[0] = 1'b0;

    // 5 levels of horiz. sum lines
    wire [4:0] s1;
    wire [4:0] s2;
    wire [4:0] s3;
    wire [4:0] s4;
    wire [4:0] s5;

    // 4 and lines per level
    wire [3:0] w1;
    wire [3:0] w2;
    wire [3:0] w3;
    wire [3:0] w4;

    //--------------- LVL 1 --------------------------
    /*
    // T1
    assign s1[0] = a[0] & b[0];
    // T2
    assign s1[1] = a[1] & b[0]; 
    // T3
    assign s1[2] = a[2] & b[0];
    // T4
    assign s1[3] = a[3] & b[0];*/
    genvar i;
    generate
        for (i = 0; i < 4; i = i + 1) begin
            assign s1[i] = a[i] & b[0];
        end
    endgenerate

    //--------------- LVL 2 --------------------------
    /*genvar j;
    generate
        for (j = 0; j < 3; j = j + 1) begin
            assign w1[j] = a[j] & b[1];
            full_adder f2(w1[j], s1[j + 1], c1[j], s2[j], c1[j + 1]);
        end
    endgenerate*/
    // T1 
    assign w1[0] = a[0] & b[1];
    full_adder f12(w1[0], s1[1], c1[0], s2[0], c1[1]); // Cin = 0 on Adder #1

    // T2
    assign w1[1] = a[1] & b[1];
    full_adder f22(w1[1], s1[2], c1[1], s2[1], c1[2]);

    // T3
    assign w1[2] = a[2] & b[1];
    full_adder f32(w1[2], s1[3], c1[2], s2[2], c1[3]);

    // T4
    assign w1[3] = a[3] & b[1];
    full_adder f42(w1[3], 1'b0, c1[3], s2[3], c1[4]); // B = 0 only this adder on L2

    /*genvar j;
    generate
        for (j = 0; j < 4; j = j + 1) begin
            assign w1[j] = a[j] & b[1];
            full_adder f(w1[j], s1[j + 1], );
        end
    endgenerate*/

    //--------------- LVL 3 --------------------------
    
    // T1
    assign w2[0] = a[0] & b[2];
    full_adder f13(w2[0], s2[1], c2[0], s3[0], c2[1]);

    // T2
    assign w2[1] = a[1] & b[2];
    full_adder f23(w2[1], s2[2], c2[1], s3[1], c2[2]);

    // T3
    assign w2[2] = a[2] & b[2];
    full_adder f33(w2[2], s2[3], c2[2], s3[2], c2[3]);
    

    /*genvar k;
    generate
        for (k = 0; k < 3; k = k + 1) begin
            assign w2[k] = a[k] & b[2];
            full_adder f3(w2[k], s2[k + 1], c2[k], s3[k], c2[k + 1]);
        end
    endgenerate*/

    // T4
    assign w2[3] = a[3] & b[2];
    full_adder f43(w2[3], c1[4], c2[3], s3[3], c2[4]); //B = last of prev Cin row on last Adder

    //--------------- LVL 4 --------------------------
    // T1
    assign w3[0] = a[0] & b[3];
    full_adder f14(w3[0], s3[1], c3[0], s4[0], c3[1]);

    // T2
    assign w3[1] = a[1] & b[3];
    full_adder f24(w3[1], s3[2], c3[1], s4[1], c3[2]);

    // T3
    assign w3[2] = a[2] & b[3];
    full_adder f34(w3[2], s3[3], c3[2], s4[2], c3[3]);

    /*genvar l;
    generate
        for (l = 0; l < 3; l = l + 1) begin
            assign w3[l] = a[l] & b[3];
            full_adder f4(w3[l], s3[l + 1], c3[l], s4[l], c3[l + 1]);
        end
    endgenerate*/

    // T4
    assign w3[3] = a[3] & b[3];
    full_adder f44(w3[3], c2[4], c3[3], s4[3], c3[4]);

    //--------------- LVL 4 --------------------------

    /*genvar m;
    generate
        for (m = 0; m < 3; m = m + 1) begin
            assign w4[m] = a[m] & 1'b0;
            full_adder f5(w4[m], s4[m + 1], c4[m], s5[m], c4[m + 1]);
        end
    endgenerate*/
    // T1
    assign w4[0] = a[0] & 1'b0;//b[4];
    full_adder f15(w4[0], s4[1], c4[0], s5[0], c4[1]);

    // T2
    assign w4[1] = a[1] & 1'b0;//b[4];
    full_adder f25(w4[1], s4[2], c4[1], s5[1], c4[2]);

    // T3
    assign w4[2] = a[2] & 1'b0;//b[4];
    full_adder f35(w4[2], s4[3], c4[2], s5[2], c4[3]);

    // T4
    assign w4[3] = a[3] & 1'b0;//b[4];
    full_adder f45(w4[3], c3[4], c4[3], s5[3], Cout);

    // Assign outputs
    assign p[0] = s1[0];
    assign p[1] = s2[0];
    assign p[2] = s3[0];
    assign p[3] = s4[0];
    assign p[4] = s5[0];
    assign p[5] = s5[1];
    assign p[6] = s5[2];
    assign p[7] = s5[3];

endmodule

4-bit-wallace/4bitwallace_tb.v
module fourbitwallace_tb;

    // Inputs
    reg signed [3:0] A;
    reg signed [3:0] B;

    wire ovf;

    // Outputs
    wire signed [7:0] prod;
    integer i,j,score;

    // Instantiate the Unit Under Test (UUT)
    fourbitwallace uut (A, B, prod, ovf);

    initial begin
        $dumpfile("gtk4bit.vcd");
        $dumpvars(0, fourbitwallace_tb);
        // Apply inputs for the whole range of A and B.
        // 16*16 = 256 inputs.
        score = 0;
        for(i=-8;i <=7;i = i+1)
            for(j=-8;j <=7;j = j+1) begin
                A <= i; 
                B <= j;
                #30;
                if ((prod == A*B) && (((ovf == 0) && (prod <= 7 || prod >= -8)) || ((ovf == 1) && (prod > 7 || prod < -8)))) begin
                    $display("%d * %d = %d prod=(%b) actual=(%b) -- CORRECT; OVF: %b", A, B, prod, prod, A*B, ovf);
                    score = score + 1;  
                end else begin
                    $display("%d * %d = %d prod=(%b) actual=%d (%b) -- INCORRECT; OVF: %b" , A, B, prod, prod, A*B, A*B, ovf);
                end
            end     
            $display("Score: %d", score);
    end
      
endmodule

4-bit-wallace/gtk4bit.vcd
$date
	Thu Feb 23 00:42:57 2023
$end
$version
	Icarus Verilog
$end
$timescale
	1s
$end
$scope module fourbitwallace_tb $end
$var wire 8 ! prod [7:0] $end
$var wire 1 " ovf $end
$var reg 4 # A [3:0] $end
$var reg 4 $ B [3:0] $end
$var integer 32 % i [31:0] $end
$var integer 32 & j [31:0] $end
$var integer 32 ' score [31:0] $end
$scope module uut $end
$var wire 4 ( aIn [3:0] $end
$var wire 4 ) bIn [3:0] $end
$var wire 1 * high_bits $end
$var wire 1 + msb_match $end
$var wire 1 " ovf $end
$var wire 1 , twosComp $end
$var wire 4 - w4 [3:0] $end
$var wire 4 . w3 [3:0] $end
$var wire 4 / w2 [3:0] $end
$var wire 4 0 w1 [3:0] $end
$var wire 5 1 s5 [4:0] $end
$var wire 5 2 s4 [4:0] $end
$var wire 5 3 s3 [4:0] $end
$var wire 5 4 s2 [4:0] $end
$var wire 5 5 s1 [4:0] $end
$var wire 8 6 p [7:0] $end
$var wire 8 7 compProd [7:0] $end
$var wire 5 8 c4 [4:0] $end
$var wire 5 9 c3 [4:0] $end
$var wire 5 : c2 [4:0] $end
$var wire 5 ; c1 [4:0] $end
$var wire 4 < b [3:0] $end
$var wire 1 = allzeros $end
$var wire 1 > allones $end
$var wire 4 ? a [3:0] $end
$var wire 1 @ Cout $end
$scope begin genblk1[0] $end
$upscope $end
$scope begin genblk1[1] $end
$upscope $end
$scope begin genblk1[2] $end
$upscope $end
$scope begin genblk1[3] $end
$upscope $end
$scope module f12 $end
$var wire 1 A Data_in_A $end
$var wire 1 B Data_in_B $end
$var wire 1 C Data_in_C $end
$var wire 1 D Data_out_Carry $end
$var wire 1 E Data_out_Sum $end
$var wire 1 F ha2_sum $end
$var wire 1 G ha2_carry $end
$var wire 1 H ha1_sum $end
$var wire 1 I ha1_carry $end
$scope module ha1 $end
$var wire 1 A Data_in_A $end
$var wire 1 B Data_in_B $end
$var wire 1 I Data_out_Carry $end
$var wire 1 H Data_out_Sum $end
$upscope $end
$scope module ha2 $end
$var wire 1 C Data_in_A $end
$var wire 1 H Data_in_B $end
$var wire 1 G Data_out_Carry $end
$var wire 1 F Data_out_Sum $end
$upscope $end
$upscope $end
$scope module f13 $end
$var wire 1 J Data_in_A $end
$var wire 1 K Data_in_B $end
$var wire 1 L Data_in_C $end
$var wire 1 M Data_out_Carry $end
$var wire 1 N Data_out_Sum $end
$var wire 1 O ha2_sum $end
$var wire 1 P ha2_carry $end
$var wire 1 Q ha1_sum $end
$var wire 1 R ha1_carry $end
$scope module ha1 $end
$var wire 1 J Data_in_A $end
$var wire 1 K Data_in_B $end
$var wire 1 R Data_out_Carry $end
$var wire 1 Q Data_out_Sum $end
$upscope $end
$scope module ha2 $end
$var wire 1 L Data_in_A $end
$var wire 1 Q Data_in_B $end
$var wire 1 P Data_out_Carry $end
$var wire 1 O Data_out_Sum $end
$upscope $end
$upscope $end
$scope module f14 $end
$var wire 1 S Data_in_A $end
$var wire 1 T Data_in_B $end
$var wire 1 U Data_in_C $end
$var wire 1 V Data_out_Carry $end
$var wire 1 W Data_out_Sum $end
$var wire 1 X ha2_sum $end
$var wire 1 Y ha2_carry $end
$var wire 1 Z ha1_sum $end
$var wire 1 [ ha1_carry $end
$scope module ha1 $end
$var wire 1 S Data_in_A $end
$var wire 1 T Data_in_B $end
$var wire 1 [ Data_out_Carry $end
$var wire 1 Z Data_out_Sum $end
$upscope $end
$scope module ha2 $end
$var wire 1 U Data_in_A $end
$var wire 1 Z Data_in_B $end
$var wire 1 Y Data_out_Carry $end
$var wire 1 X Data_out_Sum $end
$upscope $end
$upscope $end
$scope module f15 $end
$var wire 1 \ Data_in_A $end
$var wire 1 ] Data_in_B $end
$var wire 1 ^ Data_in_C $end
$var wire 1 _ Data_out_Carry $end
$var wire 1 ` Data_out_Sum $end
$var wire 1 a ha2_sum $end
$var wire 1 b ha2_carry $end
$var wire 1 c ha1_sum $end
$var wire 1 d ha1_carry $end
$scope module ha1 $end
$var wire 1 \ Data_in_A $end
$var wire 1 ] Data_in_B $end
$var wire 1 d Data_out_Carry $end
$var wire 1 c Data_out_Sum $end
$upscope $end
$scope module ha2 $end
$var wire 1 ^ Data_in_A $end
$var wire 1 c Data_in_B $end
$var wire 1 b Data_out_Carry $end
$var wire 1 a Data_out_Sum $end
$upscope $end
$upscope $end
$scope module f22 $end
$var wire 1 e Data_in_A $end
$var wire 1 f Data_in_B $end
$var wire 1 g Data_in_C $end
$var wire 1 h Data_out_Carry $end
$var wire 1 i Data_out_Sum $end
$var wire 1 j ha2_sum $end
$var wire 1 k ha2_carry $end
$var wire 1 l ha1_sum $end
$var wire 1 m ha1_carry $end
$scope module ha1 $end
$var wire 1 e Data_in_A $end
$var wire 1 f Data_in_B $end
$var wire 1 m Data_out_Carry $end
$var wire 1 l Data_out_Sum $end
$upscope $end
$scope module ha2 $end
$var wire 1 g Data_in_A $end
$var wire 1 l Data_in_B $end
$var wire 1 k Data_out_Carry $end
$var wire 1 j Data_out_Sum $end
$upscope $end
$upscope $end
$scope module f23 $end
$var wire 1 n Data_in_A $end
$var wire 1 o Data_in_B $end
$var wire 1 p Data_in_C $end
$var wire 1 q Data_out_Carry $end
$var wire 1 r Data_out_Sum $end
$var wire 1 s ha2_sum $end
$var wire 1 t ha2_carry $end
$var wire 1 u ha1_sum $end
$var wire 1 v ha1_carry $end
$scope module ha1 $end
$var wire 1 n Data_in_A $end
$var wire 1 o Data_in_B $end
$var wire 1 v Data_out_Carry $end
$var wire 1 u Data_out_Sum $end
$upscope $end
$scope module ha2 $end
$var wire 1 p Data_in_A $end
$var wire 1 u Data_in_B $end
$var wire 1 t Data_out_Carry $end
$var wire 1 s Data_out_Sum $end
$upscope $end
$upscope $end
$scope module f24 $end
$var wire 1 w Data_in_A $end
$var wire 1 x Data_in_B $end
$var wire 1 y Data_in_C $end
$var wire 1 z Data_out_Carry $end
$var wire 1 { Data_out_Sum $end
$var wire 1 | ha2_sum $end
$var wire 1 } ha2_carry $end
$var wire 1 ~ ha1_sum $end
$var wire 1 !" ha1_carry $end
$scope module ha1 $end
$var wire 1 w Data_in_A $end
$var wire 1 x Data_in_B $end
$var wire 1 !" Data_out_Carry $end
$var wire 1 ~ Data_out_Sum $end
$upscope $end
$scope module ha2 $end
$var wire 1 y Data_in_A $end
$var wire 1 ~ Data_in_B $end
$var wire 1 } Data_out_Carry $end
$var wire 1 | Data_out_Sum $end
$upscope $end
$upscope $end
$scope module f25 $end
$var wire 1 "" Data_in_A $end
$var wire 1 #" Data_in_B $end
$var wire 1 $" Data_in_C $end
$var wire 1 %" Data_out_Carry $end
$var wire 1 &" Data_out_Sum $end
$var wire 1 '" ha2_sum $end
$var wire 1 (" ha2_carry $end
$var wire 1 )" ha1_sum $end
$var wire 1 *" ha1_carry $end
$scope module ha1 $end
$var wire 1 "" Data_in_A $end
$var wire 1 #" Data_in_B $end
$var wire 1 *" Data_out_Carry $end
$var wire 1 )" Data_out_Sum $end
$upscope $end
$scope module ha2 $end
$var wire 1 $" Data_in_A $end
$var wire 1 )" Data_in_B $end
$var wire 1 (" Data_out_Carry $end
$var wire 1 '" Data_out_Sum $end
$upscope $end
$upscope $end
$scope module f32 $end
$var wire 1 +" Data_in_A $end
$var wire 1 ," Data_in_B $end
$var wire 1 -" Data_in_C $end
$var wire 1 ." Data_out_Carry $end
$var wire 1 /" Data_out_Sum $end
$var wire 1 0" ha2_sum $end
$var wire 1 1" ha2_carry $end
$var wire 1 2" ha1_sum $end
$var wire 1 3" ha1_carry $end
$scope module ha1 $end
$var wire 1 +" Data_in_A $end
$var wire 1 ," Data_in_B $end
$var wire 1 3" Data_out_Carry $end
$var wire 1 2" Data_out_Sum $end
$upscope $end
$scope module ha2 $end
$var wire 1 -" Data_in_A $end
$var wire 1 2" Data_in_B $end
$var wire 1 1" Data_out_Carry $end
$var wire 1 0" Data_out_Sum $end
$upscope $end
$upscope $end
$scope module f33 $end
$var wire 1 4" Data_in_A $end
$var wire 1 5" Data_in_B $end
$var wire 1 6" Data_in_C $end
$var wire 1 7" Data_out_Carry $end
$var wire 1 8" Data_out_Sum $end
$var wire 1 9" ha2_sum $end
$var wire 1 :" ha2_carry $end
$var wire 1 ;" ha1_sum $end
$var wire 1 <" ha1_carry $end
$scope module ha1 $end
$var wire 1 4" Data_in_A $end
$var wire 1 5" Data_in_B $end
$var wire 1 <" Data_out_Carry $end
$var wire 1 ;" Data_out_Sum $end
$upscope $end
$scope module ha2 $end
$var wire 1 6" Data_in_A $end
$var wire 1 ;" Data_in_B $end
$var wire 1 :" Data_out_Carry $end
$var wire 1 9" Data_out_Sum $end
$upscope $end
$upscope $end
$scope module f34 $end
$var wire 1 =" Data_in_A $end
$var wire 1 >" Data_in_B $end
$var wire 1 ?" Data_in_C $end
$var wire 1 @" Data_out_Carry $end
$var wire 1 A" Data_out_Sum $end
$var wire 1 B" ha2_sum $end
$var wire 1 C" ha2_carry $end
$var wire 1 D" ha1_sum $end
$var wire 1 E" ha1_carry $end
$scope module ha1 $end
$var wire 1 =" Data_in_A $end
$var wire 1 >" Data_in_B $end
$var wire 1 E" Data_out_Carry $end
$var wire 1 D" Data_out_Sum $end
$upscope $end
$scope module ha2 $end
$var wire 1 ?" Data_in_A $end
$var wire 1 D" Data_in_B $end
$var wire 1 C" Data_out_Carry $end
$var wire 1 B" Data_out_Sum $end
$upscope $end
$upscope $end
$scope module f35 $end
$var wire 1 F" Data_in_A $end
$var wire 1 G" Data_in_B $end
$var wire 1 H" Data_in_C $end
$var wire 1 I" Data_out_Carry $end
$var wire 1 J" Data_out_Sum $end
$var wire 1 K" ha2_sum $end
$var wire 1 L" ha2_carry $end
$var wire 1 M" ha1_sum $end
$var wire 1 N" ha1_carry $end
$scope module ha1 $end
$var wire 1 F" Data_in_A $end
$var wire 1 G" Data_in_B $end
$var wire 1 N" Data_out_Carry $end
$var wire 1 M" Data_out_Sum $end
$upscope $end
$scope module ha2 $end
$var wire 1 H" Data_in_A $end
$var wire 1 M" Data_in_B $end
$var wire 1 L" Data_out_Carry $end
$var wire 1 K" Data_out_Sum $end
$upscope $end
$upscope $end
$scope module f42 $end
$var wire 1 O" Data_in_A $end
$var wire 1 P" Data_in_B $end
$var wire 1 Q" Data_in_C $end
$var wire 1 R" Data_out_Carry $end
$var wire 1 S" Data_out_Sum $end
$var wire 1 T" ha2_sum $end
$var wire 1 U" ha2_carry $end
$var wire 1 V" ha1_sum $end
$var wire 1 W" ha1_carry $end
$scope module ha1 $end
$var wire 1 O" Data_in_A $end
$var wire 1 P" Data_in_B $end
$var wire 1 W" Data_out_Carry $end
$var wire 1 V" Data_out_Sum $end
$upscope $end
$scope module ha2 $end
$var wire 1 Q" Data_in_A $end
$var wire 1 V" Data_in_B $end
$var wire 1 U" Data_out_Carry $end
$var wire 1 T" Data_out_Sum $end
$upscope $end
$upscope $end
$scope module f43 $end
$var wire 1 X" Data_in_A $end
$var wire 1 Y" Data_in_B $end
$var wire 1 Z" Data_in_C $end
$var wire 1 [" Data_out_Carry $end
$var wire 1 \" Data_out_Sum $end
$var wire 1 ]" ha2_sum $end
$var wire 1 ^" ha2_carry $end
$var wire 1 _" ha1_sum $end
$var wire 1 `" ha1_carry $end
$scope module ha1 $end
$var wire 1 X" Data_in_A $end
$var wire 1 Y" Data_in_B $end
$var wire 1 `" Data_out_Carry $end
$var wire 1 _" Data_out_Sum $end
$upscope $end
$scope module ha2 $end
$var wire 1 Z" Data_in_A $end
$var wire 1 _" Data_in_B $end
$var wire 1 ^" Data_out_Carry $end
$var wire 1 ]" Data_out_Sum $end
$upscope $end
$upscope $end
$scope module f44 $end
$var wire 1 a" Data_in_A $end
$var wire 1 b" Data_in_B $end
$var wire 1 c" Data_in_C $end
$var wire 1 d" Data_out_Carry $end
$var wire 1 e" Data_out_Sum $end
$var wire 1 f" ha2_sum $end
$var wire 1 g" ha2_carry $end
$var wire 1 h" ha1_sum $end
$var wire 1 i" ha1_carry $end
$scope module ha1 $end
$var wire 1 a" Data_in_A $end
$var wire 1 b" Data_in_B $end
$var wire 1 i" Data_out_Carry $end
$var wire 1 h" Data_out_Sum $end
$upscope $end
$scope module ha2 $end
$var wire 1 c" Data_in_A $end
$var wire 1 h" Data_in_B $end
$var wire 1 g" Data_out_Carry $end
$var wire 1 f" Data_out_Sum $end
$upscope $end
$upscope $end
$scope module f45 $end
$var wire 1 j" Data_in_A $end
$var wire 1 k" Data_in_B $end
$var wire 1 l" Data_in_C $end
$var wire 1 @ Data_out_Carry $end
$var wire 1 m" Data_out_Sum $end
$var wire 1 n" ha2_sum $end
$var wire 1 o" ha2_carry $end
$var wire 1 p" ha1_sum $end
$var wire 1 q" ha1_carry $end
$scope module ha1 $end
$var wire 1 j" Data_in_A $end
$var wire 1 k" Data_in_B $end
$var wire 1 q" Data_out_Carry $end
$var wire 1 p" Data_out_Sum $end
$upscope $end
$scope module ha2 $end
$var wire 1 l" Data_in_A $end
$var wire 1 p" Data_in_B $end
$var wire 1 o" Data_out_Carry $end
$var wire 1 n" Data_out_Sum $end
$upscope $end
$upscope $end
$upscope $end
$upscope $end
$enddefinitions $end
#0
$dumpvars
0q"
0p"
0o"
0n"
0m"
0l"
0k"
0j"
0i"
1h"
0g"
1f"
1e"
0d"
0c"
0b"
1a"
0`"
0_"
0^"
0]"
0\"
0["
0Z"
0Y"
0X"
0W"
0V"
0U"
0T"
0S"
0R"
0Q"
0P"
0O"
0N"
1M"
0L"
1K"
1J"
0I"
0H"
1G"
0F"
0E"
0D"
0C"
0B"
0A"
0@"
0?"
0>"
0="
0<"
0;"
0:"
09"
08"
07"
06"
05"
04"
03"
02"
01"
00"
0/"
0."
0-"
0,"
0+"
0*"
0)"
0("
0'"
0&"
0%"
0$"
0#"
0""
0!"
0~
0}
0|
0{
0z
0y
0x
0w
0v
0u
0t
0s
0r
0q
0p
0o
0n
0m
0l
0k
0j
0i
0h
0g
0f
0e
0d
0c
0b
0a
0`
0_
0^
0]
0\
0[
0Z
0Y
0X
0W
0V
0U
0T
0S
0R
0Q
0P
0O
0N
0M
0L
0K
0J
0I
0H
0G
0F
0E
0D
0C
0B
0A
0@
b1000 ?
0>
1=
b1000 <
b0 ;
b0 :
b0 9
bz0000 8
b1000000 7
b1000000 6
bz0000 5
bz0000 4
bz0000 3
bz1000 2
bz0100 1
b0 0
b0 /
b1000 .
b0 -
0,
1+
1*
b1000 )
b1000 (
b0 '
b11111111111111111111111111111000 &
b11111111111111111111111111111000 %
b1000 $
b1000 #
1"
b1000000 !
$end
#30
1`
1a
1c
1]
0"
1{
1|
1&"
1'"
0+
1*
1W
1X
1~
1)"
1=
b111000 !
b111000 7
1Z
1x
1#"
b111000 6
1T
18"
19"
1A"
1B"
bz0011 1
0J"
0K"
1r
1s
1;"
1D"
0M"
1u
15"
1>"
0G"
1o
1S"
1T"
bz1110 3
1\"
1]"
bz0111 2
0e"
0f"
bz1100 4
1/"
10"
1V"
1_"
0h"
12"
1O"
1X"
0a"
1,"
b1000 0
b1000 /
b0 .
bz1000 5
b111 <
b1001 $
b1001 )
b11111111111111111111111111111001 &
b1 '
#60
1"
1+
b110000 !
b110000 7
b110000 6
bz0110 2
0W
0X
0Z
0T
bz1100 3
0r
0s
0u
0o
bz1000 4
0/"
00"
02"
0,"
bz0000 5
b110 <
b1010 $
b1010 )
b11111111111111111111111111111010 &
b10 '
#90
0"
bz0010 1
0`
0a
0+
0c
b101000 !
b101000 7
0]
b101000 6
0{
0|
bz0101 2
1W
1X
0~
1Z
0x
1T
08"
09"
bz1010 3
1r
1s
0;"
1u
05"
1o
0S"
0T"
bz0100 4
1/"
10"
0V"
12"
0O"
1,"
b0 0
bz1000 5
b101 <
b1011 $
b1011 )
b11111111111111111111111111111011 &
b11 '
#120
1"
1+
b100000 !
b100000 7
b100000 6
bz0100 2
0W
0X
0Z
0T
bz1000 3
0r
0s
0u
0o
bz0000 4
0/"
00"
02"
0,"
bz0000 5
b100 <
b1100 $
b1100 )
b11111111111111111111111111111100 &
b100 '
#150
0+
0"
1`
1a
1*
1c
1=
b11000 !
b11000 7
1]
b11000 6
1{
1|
bz0001 1
0&"
0'"
1W
1X
1~
0)"
1Z
1x
0#"
1T
18"
19"
bz0011 2
0A"
0B"
1r
1s
1;"
0D"
1u
15"
0>"
1o
1S"
1T"
bz0110 3
0\"
0]"
bz1100 4
1/"
10"
1V"
0_"
12"
1O"
0X"
1,"
b1000 0
b0 /
bz1000 5
b11 <
b1101 $
b1101 )
b11111111111111111111111111111101 &
b101 '
#180
1"
1+
b10000 !
b10000 7
b10000 6
bz0010 2
0W
0X
0Z
0T
bz0100 3
0r
0s
0u
0o
bz1000 4
0/"
00"
02"
0,"
bz0000 5
b10 <
b1110 $
b1110 )
b11111111111111111111111111111110 &
b110 '
#210
0*
0=
0"
bz0000 1
0`
0a
1+
0c
b1000 !
b1000 7
0]
b1000 6
0{
0|
bz0001 2
1W
1X
0~
1Z
0x
1T
08"
09"
bz0010 3
1r
1s
0;"
1u
05"
1o
0S"
0T"
bz0100 4
1/"
10"
0V"
12"
0O"
1,"
b0 0
bz1000 5
b1 <
b1111 $
b1111 )
b11111111111111111111111111111111 &
b111 '
#240
0+
b0 6
bz0000 2
0W
0X
0Z
0T
bz0000 3
0r
0s
0u
0o
bz0000 4
0/"
00"
02"
0,"
bz0000 5
b0 !
b0 7
1,
b0 <
b0 $
b0 )
b0 &
b1000 '
#270
1+
b11111000 !
b11111000 7
b1000 6
bz0001 2
1W
1X
1Z
1T
bz0010 3
1r
1s
1u
1o
bz0100 4
1/"
10"
12"
1,"
bz1000 5
b1 <
b1 $
b1 )
b1 &
b1001 '
#300
1"
1*
1=
bz0001 1
1`
1a
1+
b11110000 !
b11110000 7
1c
1]
b10000 6
1{
1|
bz0010 2
0W
0X
1~
0Z
1x
0T
18"
19"
bz0100 3
0r
0s
1;"
0u
15"
0o
1S"
1T"
bz1000 4
0/"
00"
1V"
02"
1O"
0,"
b1000 0
bz0000 5
b10 <
b10 $
b10 )
b10 &
b1010 '
#330
0"
0+
b11101000 !
b11101000 7
b11000 6
bz0011 2
1W
1X
1Z
1T
bz0110 3
1r
1s
1u
1o
bz1100 4
1/"
10"
12"
1,"
bz1000 5
b11 <
b11 $
b11 )
b11 &
b1011 '
#360
1"
0`
0a
1+
b11100000 !
b11100000 7
0c
0]
b100000 6
0{
0|
bz0010 1
1&"
1'"
0W
0X
0~
1)"
0Z
0x
1#"
0T
08"
09"
bz0100 2
1A"
1B"
0r
0s
0;"
1D"
0u
05"
1>"
0o
0S"
0T"
bz1000 3
1\"
1]"
bz0000 4
0/"
00"
0V"
1_"
02"
0O"
1X"
0,"
b0 0
b1000 /
bz0000 5
b100 <
b100 $
b100 )
b100 &
b1100 '
#390
0"
0+
b11011000 !
b11011000 7
b101000 6
bz0101 2
1W
1X
1Z
1T
bz1010 3
1r
1s
1u
1o
bz0100 4
1/"
10"
12"
1,"
bz1000 5
b101 <
b101 $
b101 )
b101 &
b1101 '
#420
1"
bz0011 1
1`
1a
1+
b11010000 !
b11010000 7
1c
1]
b110000 6
1{
1|
bz0110 2
0W
0X
1~
0Z
1x
0T
18"
19"
bz1100 3
0r
0s
1;"
0u
15"
0o
1S"
1T"
bz1000 4
0/"
00"
1V"
02"
1O"
0,"
b1000 0
bz0000 5
b110 <
b110 $
b110 )
b110 &
b1110 '
#450
0"
0+
b11001000 !
b11001000 7
b111000 6
bz0111 2
1W
1X
1Z
1T
bz1110 3
1r
1s
1u
1o
bz1100 4
1/"
10"
12"
1,"
bz1000 5
b111 <
b111 $
b111 )
b111 &
b1111 '
#480
0}
1*
1=
0J"
0K"
0x
0"
0M"
0T
08"
09"
0C"
0+
1`
1a
bz0011 1
1&"
1'"
0G"
0r
0s
0;"
1c
1)"
0e"
0f"
0u
05"
0>"
b111000 6
0y
1]
0?"
1#"
0c"
0o
0S"
0T"
bz0000 3
0\"
0]"
1W
1X
0V
1{
1|
0z
bz0111 2
1A"
1B"
b0 9
0@"
bz0000 4
0/"
00"
0V"
0_"
1Z
0[
1~
0!"
1D"
0E"
02"
0O"
0X"
1S
1w
1="
0,"
b111000 !
b111000 7
b0 0
b0 /
b111 .
bz0000 5
0,
b111 ?
b1000 <
b1000 $
b1000 )
b1001 #
b1001 (
b11111111111111111111111111111001 %
b11111111111111111111111111111000 &
b10000 '
#510
1>"
1\"
1]"
1Z"
1<"
1t
17"
1*
15"
1p
0:"
1=
1S"
1T"
1M
16"
1"
1Q"
1R
b1110 :
1q
1+
1`
1a
bz0011 1
1&"
1'"
1."
1K
0v
1c
1)"
11"
1i
1j
0o
0T
1x
1]
1#"
1-"
1g
bz1010 4
0/"
00"
0N
0O
0r
0s
bz1100 3
18"
19"
0W
0X
1{
1|
bz0110 2
1A"
1B"
1h
b1110 ;
1D
12"
0Q
1u
0;"
0Z
1~
1D"
1m
1I
b110001 !
b110001 7
1A
1e
1+"
1J
1n
14"
0S
0w
0="
1f
1B
b110001 6
b111 0
b111 /
b0 .
bz0111 5
b111 <
b1001 $
b1001 )
b11111111111111111111111111111001 &
b10001 '
#540
1*
1=
0`
0a
bz0010 1
1&"
1'"
0c
1)"
0"
0]
1#"
0+
0{
0|
1A"
1B"
0~
1D"
0x
1>"
bz0101 2
1W
1X
08"
09"
1:"
1\"
1]"
1Z
1Z"
1T
17"
1r
1s
16"
1;"
0<"
1q
05"
0t
0S"
0T"
1p
0u
1v
0Q"
bz1010 3
0N
0O
b1110 :
1M
1o
0."
0Q
1R
1/"
10"
01"
1K
0-"
0g
1i
1j
0k
0h
bz0111 4
1E
1F
b0 ;
0D
1l
0m
1H
0I
b101010 !
b101010 7
0f
0B
b101010 6
bz0000 5
b110 <
b1010 $
b1010 )
b11111111111111111111111111111010 &
b10010 '
