32-wallace/new32/new32wallace.v
module half_adder(
    Data_in_A,
    Data_in_B,
    Data_out_Sum,
    Data_out_Carry
    );

    //what are the input ports.
    input Data_in_A;
    input Data_in_B;
    //What are the output ports.
    output Data_out_Sum;
     output Data_out_Carry;
     
     //Implement the Sum and Carry equations using Verilog Bit operators.
     assign Data_out_Sum = Data_in_A ^ Data_in_B;  //XOR operation
     assign Data_out_Carry = Data_in_A & Data_in_B; //AND operation
    
endmodule

module full_adder(
    Data_in_A,  //input A
    Data_in_B,  //input B
    Data_in_C,  //input C
     Data_out_Sum,
     Data_out_Carry
    );

    //what are the input ports.
    input Data_in_A;
    input Data_in_B;
     input Data_in_C;
    //What are the output ports.
    output Data_out_Sum;
     output Data_out_Carry;
     //Internal variables
     wire ha1_sum;
     wire ha2_sum;
     wire ha1_carry;
     wire ha2_carry;
     wire Data_out_Sum;
     wire Data_out_Carry;

     //Instantiate the half adder 1
    half_adder  ha1(
        .Data_in_A(Data_in_A),
        .Data_in_B(Data_in_B),
        .Data_out_Sum(ha1_sum),
        .Data_out_Carry(ha1_carry)
    );
    
    //Instantiate the half adder 2
    half_adder  ha2(
        .Data_in_A(Data_in_C),
        .Data_in_B(ha1_sum),
        .Data_out_Sum(ha2_sum),
        .Data_out_Carry(ha2_carry)
    );

    //sum output from 2nd half adder is connected to full adder output
    assign Data_out_Sum = ha2_sum;  
    //The carry's from both the half adders are OR'ed to get the final carry./
    assign Data_out_Carry = ha1_carry | ha2_carry;
    
endmodule

module new32wallace(aIn, bIn, out, ovf);
    input [3:0] aIn, bIn;
    output [3:0] out;
    output ovf;

    wire [7:0] compProd;

    wire twosComp;
    assign twosComp = aIn[3] ^ bIn[3];

    wire [3:0] a, b;
    assign a = aIn[3] ? (~aIn) + 1 : aIn; // 2s comp A to positive
    assign b = bIn[3] ? (~bIn) + 1 : bIn; // 2s comp B to positive

    // if toggle flag = 1 then twos comp product
    wire [7:0] p;
    assign compProd = twosComp ? (~p) + 1 : p;

    wire allones, allzeros, high_bits, msb_match;
	assign allones = & compProd[7:4];
	assign allzeros = | compProd[7:4];
	assign high_bits = allones ^ allzeros; //ovf = 1 if !allzeros and !allones
	assign msb_match = allzeros ^ compProd[3];
	assign ovf = high_bits | msb_match;

    assign out = compProd[3:0];

    wire Cout;

    // 4 levels of horiz. cout lines
    wire [4:0] c1;
    wire [4:0] c2;
    wire [4:0] c3;
    wire [4:0] c4;

    assign c1[0] = 1'b0;
    assign c2[0] = 1'b0;
    assign c3[0] = 1'b0;
    assign c4[0] = 1'b0;

    // 5 levels of horiz. sum lines
    wire [4:0] s1;
    wire [4:0] s2;
    wire [4:0] s3;
    wire [4:0] s4;
    wire [4:0] s5;

    // 4 and lines per level
    wire [3:0] w1;
    wire [3:0] w2;
    wire [3:0] w3;
    wire [3:0] w4;

    //--------------- LVL 1 --------------------------

    genvar i;
    generate
        for (i = 0; i < 4; i = i + 1) begin
            assign s1[i] = a[i] & b[0];
        end
    endgenerate

    //--------------- LVL 2 --------------------------
    genvar j;
    generate
        for (j = 0; j < 3; j = j + 1) begin
            assign w1[j] = a[j] & b[1];
            full_adder f2(w1[j], s1[j + 1], c1[j], s2[j], c1[j + 1]);
        end
    endgenerate

    // T4
    assign w1[3] = a[3] & b[1];
    full_adder f42(w1[3], 1'b0, c1[3], s2[3], c1[4]); // B = 0 only this adder on L2


    //--------------- LVL 3 --------------------------

    genvar k;
    generate
        for (k = 0; k < 3; k = k + 1) begin
            assign w2[k] = a[k] & b[2];
            full_adder f3(w2[k], s2[k + 1], c2[k], s3[k], c2[k + 1]);
        end
    endgenerate

    // T4
    assign w2[3] = a[3] & b[2];
    full_adder f43(w2[3], c1[4], c2[3], s3[3], c2[4]); //B = last of prev Cin row on last Adder

    //--------------- LVL 4 --------------------------

    genvar l;
    generate
        for (l = 0; l < 3; l = l + 1) begin
            assign w3[l] = a[l] & b[3];
            full_adder f4(w3[l], s3[l + 1], c3[l], s4[l], c3[l + 1]);
        end
    endgenerate

    // T4
    assign w3[3] = a[3] & b[3];
    full_adder f44(w3[3], c2[4], c3[3], s4[3], c3[4]);

    //--------------- LVL 4 --------------------------

    genvar m;
    generate
        for (m = 0; m < 3; m = m + 1) begin
            assign w4[m] = a[m] & 1'b0;
            full_adder f5(w4[m], s4[m + 1], c4[m], s5[m], c4[m + 1]);
        end
    endgenerate

    // T4
    assign w4[3] = a[3] & 1'b0;//b[4];
    full_adder f45(w4[3], c3[4], c4[3], s5[3], Cout);

    // Assign outputs
    assign p[0] = s1[0];
    assign p[1] = s2[0];
    assign p[2] = s3[0];
    assign p[3] = s4[0];
    assign p[4] = s5[0];
    assign p[5] = s5[1];
    assign p[6] = s5[2];
    assign p[7] = s5[3];

endmodule

32-wallace/new32/tb_new32.v
module new32_tb;

    // Inputs
    reg signed [3:0] A;
    reg signed [3:0] B;

    wire ovf;

    // Outputs
    wire signed [3:0] prod;
    integer i,j,score;

    // Instantiate the Unit Under Test (UUT)
    new32wallace uut (A, B, prod, ovf);

    wire signed [7:0] lA, lB;

    assign lA = A;
    assign lB = B;

    initial begin
        $dumpfile("gtk32bit.vcd");
        $dumpvars(0, new32_tb);
        // Apply inputs for the whole range of A and B.
        // 16*16 = 256 inputs.
        score = 0;
        for(i=-8;i <=7;i = i+1)
            for(j=-8;j <=7;j = j+1) begin
                A <= i; 
                B <= j;
                #30;
                if ((prod == A*B)) begin
                    $display("%d * %d = %d prod=(%b) actual=(%b) -- CORRECT; OVF: %b", A, B, prod, prod, lA*lB, ovf);
                    score = score + 1;  
                end else begin
                    $display("%d * %d = %d prod=(%b) actual=%d (%b) -- INCORRECT; OVF: %b" , A, B, prod, prod, A*B, A*B, ovf);
                end
                
                if (((ovf == 0) * (A*B < -8 || A*B> 7)) || ((ovf == 1) * (A*B >= -8 && A*B <= 7))) begin
                    $display("INCORRECT OVF");
                end
            end     
            A <= 7;
            B <= 7;
            #30;
            $display("%d * %d = %d prod=(%b) actual=(%b); OVF: %b", A, B, prod, prod, lA*lB, ovf);
            $display("Score: %d", score);
    end
      
endmodule

32-wallace/new32/gtk32bit.vcd
$date
	Thu Feb 23 01:20:21 2023
$end
$version
	Icarus Verilog
$end
$timescale
	1s
$end
$scope module new32_tb $end
$var wire 4 ! prod [3:0] $end
$var wire 1 " ovf $end
$var wire 8 # lB [7:0] $end
$var wire 8 $ lA [7:0] $end
$var reg 4 % A [3:0] $end
$var reg 4 & B [3:0] $end
$var integer 32 ' i [31:0] $end
$var integer 32 ( j [31:0] $end
$var integer 32 ) score [31:0] $end
$scope module uut $end
$var wire 4 * aIn [3:0] $end
$var wire 4 + bIn [3:0] $end
$var wire 1 , high_bits $end
$var wire 1 - msb_match $end
$var wire 1 " ovf $end
$var wire 1 . twosComp $end
$var wire 4 / w4 [3:0] $end
$var wire 4 0 w3 [3:0] $end
$var wire 4 1 w2 [3:0] $end
$var wire 4 2 w1 [3:0] $end
$var wire 5 3 s5 [4:0] $end
$var wire 5 4 s4 [4:0] $end
$var wire 5 5 s3 [4:0] $end
$var wire 5 6 s2 [4:0] $end
$var wire 5 7 s1 [4:0] $end
$var wire 8 8 p [7:0] $end
$var wire 4 9 out [3:0] $end
$var wire 8 : compProd [7:0] $end
$var wire 5 ; c4 [4:0] $end
$var wire 5 < c3 [4:0] $end
$var wire 5 = c2 [4:0] $end
$var wire 5 > c1 [4:0] $end
$var wire 4 ? b [3:0] $end
$var wire 1 @ allzeros $end
$var wire 1 A allones $end
$var wire 4 B a [3:0] $end
$var wire 1 C Cout $end
$scope begin genblk1[0] $end
$upscope $end
$scope begin genblk1[1] $end
$upscope $end
$scope begin genblk1[2] $end
$upscope $end
$scope begin genblk1[3] $end
$upscope $end
$scope begin genblk2[0] $end
$scope module f2 $end
$var wire 1 D Data_in_A $end
$var wire 1 E Data_in_B $end
$var wire 1 F Data_in_C $end
$var wire 1 G Data_out_Carry $end
$var wire 1 H Data_out_Sum $end
$var wire 1 I ha2_sum $end
$var wire 1 J ha2_carry $end
$var wire 1 K ha1_sum $end
$var wire 1 L ha1_carry $end
$scope module ha1 $end
$var wire 1 D Data_in_A $end
$var wire 1 E Data_in_B $end
$var wire 1 L Data_out_Carry $end
$var wire 1 K Data_out_Sum $end
$upscope $end
$scope module ha2 $end
$var wire 1 F Data_in_A $end
$var wire 1 K Data_in_B $end
$var wire 1 J Data_out_Carry $end
$var wire 1 I Data_out_Sum $end
$upscope $end
$upscope $end
$upscope $end
$scope begin genblk2[1] $end
$scope module f2 $end
$var wire 1 M Data_in_A $end
$var wire 1 N Data_in_B $end
$var wire 1 O Data_in_C $end
$var wire 1 P Data_out_Carry $end
$var wire 1 Q Data_out_Sum $end
$var wire 1 R ha2_sum $end
$var wire 1 S ha2_carry $end
$var wire 1 T ha1_sum $end
$var wire 1 U ha1_carry $end
$scope module ha1 $end
$var wire 1 M Data_in_A $end
$var wire 1 N Data_in_B $end
$var wire 1 U Data_out_Carry $end
$var wire 1 T Data_out_Sum $end
$upscope $end
$scope module ha2 $end
$var wire 1 O Data_in_A $end
$var wire 1 T Data_in_B $end
$var wire 1 S Data_out_Carry $end
$var wire 1 R Data_out_Sum $end
$upscope $end
$upscope $end
$upscope $end
$scope begin genblk2[2] $end
$scope module f2 $end
$var wire 1 V Data_in_A $end
$var wire 1 W Data_in_B $end
$var wire 1 X Data_in_C $end
$var wire 1 Y Data_out_Carry $end
$var wire 1 Z Data_out_Sum $end
$var wire 1 [ ha2_sum $end
$var wire 1 \ ha2_carry $end
$var wire 1 ] ha1_sum $end
$var wire 1 ^ ha1_carry $end
$scope module ha1 $end
$var wire 1 V Data_in_A $end
$var wire 1 W Data_in_B $end
$var wire 1 ^ Data_out_Carry $end
$var wire 1 ] Data_out_Sum $end
$upscope $end
$scope module ha2 $end
$var wire 1 X Data_in_A $end
$var wire 1 ] Data_in_B $end
$var wire 1 \ Data_out_Carry $end
$var wire 1 [ Data_out_Sum $end
$upscope $end
$upscope $end
$upscope $end
$scope begin genblk3[0] $end
$scope module f3 $end
$var wire 1 _ Data_in_A $end
$var wire 1 ` Data_in_B $end
$var wire 1 a Data_in_C $end
$var wire 1 b Data_out_Carry $end
$var wire 1 c Data_out_Sum $end
$var wire 1 d ha2_sum $end
$var wire 1 e ha2_carry $end
$var wire 1 f ha1_sum $end
$var wire 1 g ha1_carry $end
$scope module ha1 $end
$var wire 1 _ Data_in_A $end
$var wire 1 ` Data_in_B $end
$var wire 1 g Data_out_Carry $end
$var wire 1 f Data_out_Sum $end
$upscope $end
$scope module ha2 $end
$var wire 1 a Data_in_A $end
$var wire 1 f Data_in_B $end
$var wire 1 e Data_out_Carry $end
$var wire 1 d Data_out_Sum $end
$upscope $end
$upscope $end
$upscope $end
$scope begin genblk3[1] $end
$scope module f3 $end
$var wire 1 h Data_in_A $end
$var wire 1 i Data_in_B $end
$var wire 1 j Data_in_C $end
$var wire 1 k Data_out_Carry $end
$var wire 1 l Data_out_Sum $end
$var wire 1 m ha2_sum $end
$var wire 1 n ha2_carry $end
$var wire 1 o ha1_sum $end
$var wire 1 p ha1_carry $end
$scope module ha1 $end
$var wire 1 h Data_in_A $end
$var wire 1 i Data_in_B $end
$var wire 1 p Data_out_Carry $end
$var wire 1 o Data_out_Sum $end
$upscope $end
$scope module ha2 $end
$var wire 1 j Data_in_A $end
$var wire 1 o Data_in_B $end
$var wire 1 n Data_out_Carry $end
$var wire 1 m Data_out_Sum $end
$upscope $end
$upscope $end
$upscope $end
$scope begin genblk3[2] $end
$scope module f3 $end
$var wire 1 q Data_in_A $end
$var wire 1 r Data_in_B $end
$var wire 1 s Data_in_C $end
$var wire 1 t Data_out_Carry $end
$var wire 1 u Data_out_Sum $end
$var wire 1 v ha2_sum $end
$var wire 1 w ha2_carry $end
$var wire 1 x ha1_sum $end
$var wire 1 y ha1_carry $end
$scope module ha1 $end
$var wire 1 q Data_in_A $end
$var wire 1 r Data_in_B $end
$var wire 1 y Data_out_Carry $end
$var wire 1 x Data_out_Sum $end
$upscope $end
$scope module ha2 $end
$var wire 1 s Data_in_A $end
$var wire 1 x Data_in_B $end
$var wire 1 w Data_out_Carry $end
$var wire 1 v Data_out_Sum $end
$upscope $end
$upscope $end
$upscope $end
$scope begin genblk4[0] $end
$scope module f4 $end
$var wire 1 z Data_in_A $end
$var wire 1 { Data_in_B $end
$var wire 1 | Data_in_C $end
$var wire 1 } Data_out_Carry $end
$var wire 1 ~ Data_out_Sum $end
$var wire 1 !" ha2_sum $end
$var wire 1 "" ha2_carry $end
$var wire 1 #" ha1_sum $end
$var wire 1 $" ha1_carry $end
$scope module ha1 $end
$var wire 1 z Data_in_A $end
$var wire 1 { Data_in_B $end
$var wire 1 $" Data_out_Carry $end
$var wire 1 #" Data_out_Sum $end
$upscope $end
$scope module ha2 $end
$var wire 1 | Data_in_A $end
$var wire 1 #" Data_in_B $end
$var wire 1 "" Data_out_Carry $end
$var wire 1 !" Data_out_Sum $end
$upscope $end
$upscope $end
$upscope $end
$scope begin genblk4[1] $end
$scope module f4 $end
$var wire 1 %" Data_in_A $end
$var wire 1 &" Data_in_B $end
$var wire 1 '" Data_in_C $end
$var wire 1 (" Data_out_Carry $end
$var wire 1 )" Data_out_Sum $end
$var wire 1 *" ha2_sum $end
$var wire 1 +" ha2_carry $end
$var wire 1 ," ha1_sum $end
$var wire 1 -" ha1_carry $end
$scope module ha1 $end
$var wire 1 %" Data_in_A $end
$var wire 1 &" Data_in_B $end
$var wire 1 -" Data_out_Carry $end
$var wire 1 ," Data_out_Sum $end
$upscope $end
$scope module ha2 $end
$var wire 1 '" Data_in_A $end
$var wire 1 ," Data_in_B $end
$var wire 1 +" Data_out_Carry $end
$var wire 1 *" Data_out_Sum $end
$upscope $end
$upscope $end
$upscope $end
$scope begin genblk4[2] $end
$scope module f4 $end
$var wire 1 ." Data_in_A $end
$var wire 1 /" Data_in_B $end
$var wire 1 0" Data_in_C $end
$var wire 1 1" Data_out_Carry $end
$var wire 1 2" Data_out_Sum $end
$var wire 1 3" ha2_sum $end
$var wire 1 4" ha2_carry $end
$var wire 1 5" ha1_sum $end
$var wire 1 6" ha1_carry $end
$scope module ha1 $end
$var wire 1 ." Data_in_A $end
$var wire 1 /" Data_in_B $end
$var wire 1 6" Data_out_Carry $end
$var wire 1 5" Data_out_Sum $end
$upscope $end
$scope module ha2 $end
$var wire 1 0" Data_in_A $end
$var wire 1 5" Data_in_B $end
$var wire 1 4" Data_out_Carry $end
$var wire 1 3" Data_out_Sum $end
$upscope $end
$upscope $end
$upscope $end
$scope begin genblk5[0] $end
$scope module f5 $end
$var wire 1 7" Data_in_A $end
$var wire 1 8" Data_in_B $end
$var wire 1 9" Data_in_C $end
$var wire 1 :" Data_out_Carry $end
$var wire 1 ;" Data_out_Sum $end
$var wire 1 <" ha2_sum $end
$var wire 1 =" ha2_carry $end
$var wire 1 >" ha1_sum $end
$var wire 1 ?" ha1_carry $end
$scope module ha1 $end
$var wire 1 7" Data_in_A $end
$var wire 1 8" Data_in_B $end
$var wire 1 ?" Data_out_Carry $end
$var wire 1 >" Data_out_Sum $end
$upscope $end
$scope module ha2 $end
$var wire 1 9" Data_in_A $end
$var wire 1 >" Data_in_B $end
$var wire 1 =" Data_out_Carry $end
$var wire 1 <" Data_out_Sum $end
$upscope $end
$upscope $end
$upscope $end
$scope begin genblk5[1] $end
$scope module f5 $end
$var wire 1 @" Data_in_A $end
$var wire 1 A" Data_in_B $end
$var wire 1 B" Data_in_C $end
$var wire 1 C" Data_out_Carry $end
$var wire 1 D" Data_out_Sum $end
$var wire 1 E" ha2_sum $end
$var wire 1 F" ha2_carry $end
$var wire 1 G" ha1_sum $end
$var wire 1 H" ha1_carry $end
$scope module ha1 $end
$var wire 1 @" Data_in_A $end
$var wire 1 A" Data_in_B $end
$var wire 1 H" Data_out_Carry $end
$var wire 1 G" Data_out_Sum $end
$upscope $end
$scope module ha2 $end
$var wire 1 B" Data_in_A $end
$var wire 1 G" Data_in_B $end
$var wire 1 F" Data_out_Carry $end
$var wire 1 E" Data_out_Sum $end
$upscope $end
$upscope $end
$upscope $end
$scope begin genblk5[2] $end
$scope module f5 $end
$var wire 1 I" Data_in_A $end
$var wire 1 J" Data_in_B $end
$var wire 1 K" Data_in_C $end
$var wire 1 L" Data_out_Carry $end
$var wire 1 M" Data_out_Sum $end
$var wire 1 N" ha2_sum $end
$var wire 1 O" ha2_carry $end
$var wire 1 P" ha1_sum $end
$var wire 1 Q" ha1_carry $end
$scope module ha1 $end
$var wire 1 I" Data_in_A $end
$var wire 1 J" Data_in_B $end
$var wire 1 Q" Data_out_Carry $end
$var wire 1 P" Data_out_Sum $end
$upscope $end
$scope module ha2 $end
$var wire 1 K" Data_in_A $end
$var wire 1 P" Data_in_B $end
$var wire 1 O" Data_out_Carry $end
$var wire 1 N" Data_out_Sum $end
$upscope $end
$upscope $end
$upscope $end
$scope module f42 $end
$var wire 1 R" Data_in_A $end
$var wire 1 S" Data_in_B $end
$var wire 1 T" Data_in_C $end
$var wire 1 U" Data_out_Carry $end
$var wire 1 V" Data_out_Sum $end
$var wire 1 W" ha2_sum $end
$var wire 1 X" ha2_carry $end
$var wire 1 Y" ha1_sum $end
$var wire 1 Z" ha1_carry $end
$scope module ha1 $end
$var wire 1 R" Data_in_A $end
$var wire 1 S" Data_in_B $end
$var wire 1 Z" Data_out_Carry $end
$var wire 1 Y" Data_out_Sum $end
$upscope $end
$scope module ha2 $end
$var wire 1 T" Data_in_A $end
$var wire 1 Y" Data_in_B $end
$var wire 1 X" Data_out_Carry $end
$var wire 1 W" Data_out_Sum $end
$upscope $end
$upscope $end
$scope module f43 $end
$var wire 1 [" Data_in_A $end
$var wire 1 \" Data_in_B $end
$var wire 1 ]" Data_in_C $end
$var wire 1 ^" Data_out_Carry $end
$var wire 1 _" Data_out_Sum $end
$var wire 1 `" ha2_sum $end
$var wire 1 a" ha2_carry $end
$var wire 1 b" ha1_sum $end
$var wire 1 c" ha1_carry $end
$scope module ha1 $end
$var wire 1 [" Data_in_A $end
$var wire 1 \" Data_in_B $end
$var wire 1 c" Data_out_Carry $end
$var wire 1 b" Data_out_Sum $end
$upscope $end
$scope module ha2 $end
$var wire 1 ]" Data_in_A $end
$var wire 1 b" Data_in_B $end
$var wire 1 a" Data_out_Carry $end
$var wire 1 `" Data_out_Sum $end
$upscope $end
$upscope $end
$scope module f44 $end
$var wire 1 d" Data_in_A $end
$var wire 1 e" Data_in_B $end
$var wire 1 f" Data_in_C $end
$var wire 1 g" Data_out_Carry $end
$var wire 1 h" Data_out_Sum $end
$var wire 1 i" ha2_sum $end
$var wire 1 j" ha2_carry $end
$var wire 1 k" ha1_sum $end
$var wire 1 l" ha1_carry $end
$scope module ha1 $end
$var wire 1 d" Data_in_A $end
$var wire 1 e" Data_in_B $end
$var wire 1 l" Data_out_Carry $end
$var wire 1 k" Data_out_Sum $end
$upscope $end
$scope module ha2 $end
$var wire 1 f" Data_in_A $end
$var wire 1 k" Data_in_B $end
$var wire 1 j" Data_out_Carry $end
$var wire 1 i" Data_out_Sum $end
$upscope $end
$upscope $end
$scope module f45 $end
$var wire 1 m" Data_in_A $end
$var wire 1 n" Data_in_B $end
$var wire 1 o" Data_in_C $end
$var wire 1 C Data_out_Carry $end
$var wire 1 p" Data_out_Sum $end
$var wire 1 q" ha2_sum $end
$var wire 1 r" ha2_carry $end
$var wire 1 s" ha1_sum $end
$var wire 1 t" ha1_carry $end
$scope module ha1 $end
$var wire 1 m" Data_in_A $end
$var wire 1 n" Data_in_B $end
$var wire 1 t" Data_out_Carry $end
$var wire 1 s" Data_out_Sum $end
$upscope $end
$scope module ha2 $end
$var wire 1 o" Data_in_A $end
$var wire 1 s" Data_in_B $end
$var wire 1 r" Data_out_Carry $end
$var wire 1 q" Data_out_Sum $end
$upscope $end
$upscope $end
$upscope $end
$upscope $end
$enddefinitions $end
#0
$dumpvars
0t"
0s"
0r"
0q"
0p"
0o"
0n"
0m"
0l"
1k"
0j"
1i"
1h"
0g"
0f"
0e"
1d"
0c"
0b"
0a"
0`"
0_"
0^"
0]"
0\"
0["
0Z"
0Y"
0X"
0W"
0V"
0U"
0T"
0S"
0R"
0Q"
1P"
0O"
1N"
1M"
0L"
0K"
1J"
0I"
0H"
0G"
0F"
0E"
0D"
0C"
0B"
0A"
0@"
0?"
0>"
0="
0<"
0;"
0:"
09"
08"
07"
06"
05"
04"
03"
02"
01"
00"
0/"
0."
0-"
0,"
0+"
0*"
0)"
0("
0'"
0&"
0%"
0$"
0#"
0""
0!"
0~
0}
0|
0{
0z
0y
0x
0w
0v
0u
0t
0s
0r
0q
0p
0o
0n
0m
0l
0k
0j
0i
0h
0g
0f
0e
0d
0c
0b
0a
0`
0_
0^
0]
0\
0[
0Z
0Y
0X
0W
0V
0U
0T
0S
0R
0Q
0P
0O
0N
0M
0L
0K
0J
0I
0H
0G
0F
0E
0D
0C
b1000 B
0A
1@
b1000 ?
b0 >
b0 =
b0 <
bz0000 ;
b1000000 :
b0 9
b1000000 8
bz0000 7
bz0000 6
bz0000 5
bz1000 4
bz0100 3
b0 2
b0 1
b1000 0
b0 /
0.
1-
1,
b1000 +
b1000 *
b0 )
b11111111111111111111111111111000 (
b11111111111111111111111111111000 '
b1000 &
b1000 %
b11111000 $
b11111000 #
1"
b0 !
$end
#30
1;"
1<"
b1000 !
b1000 9
1>"
1"
18"
0-
1,
1)"
1*"
1D"
1E"
1@
1~
1!"
1,"
1G"
b111000 :
1#"
1&"
1A"
b111000 8
1{
1u
1v
12"
13"
bz0011 3
0M"
0N"
1l
1m
1x
15"
0P"
1o
1r
1/"
0J"
1i
1V"
1W"
bz1110 5
1_"
1`"
bz0111 4
0h"
0i"
bz1100 6
1Z
1[
1Y"
1b"
0k"
1]
1R"
1["
0d"
1W
b1000 2
b1000 1
b0 0
bz1000 7
b111 ?
b11111001 #
b1001 &
b1001 +
b11111111111111111111111111111001 (
b1 )
#60
1-
b0 !
b0 9
b110000 :
b110000 8
bz0110 4
0~
0!"
0#"
0{
bz1100 5
0l
0m
0o
0i
bz1000 6
0Z
0[
0]
0W
bz0000 7
b110 ?
b11111010 #
b1010 &
b1010 +
b11111111111111111111111111111010 (
b10 )
#90
0-
bz0010 3
0;"
0<"
b1000 !
b1000 9
0>"
b101000 :
08"
b101000 8
0)"
0*"
bz0101 4
1~
1!"
0,"
1#"
0&"
1{
0u
0v
bz1010 5
1l
1m
0x
1o
0r
1i
0V"
0W"
bz0100 6
1Z
1[
0Y"
1]
0R"
1W
b0 2
bz1000 7
b101 ?
b11111011 #
b1011 &
b1011 +
b11111111111111111111111111111011 (
b11 )
#120
1-
b0 !
b0 9
b100000 :
b100000 8
bz0100 4
0~
0!"
0#"
0{
bz1000 5
0l
0m
0o
0i
bz0000 6
0Z
0[
0]
0W
bz0000 7
b100 ?
b11111100 #
b1100 &
b1100 +
b11111111111111111111111111111100 (
b100 )
#150
0-
1,
1;"
1<"
1@
b1000 !
b1000 9
1>"
b11000 :
18"
b11000 8
1)"
1*"
bz0001 3
0D"
0E"
1~
1!"
1,"
0G"
1#"
1&"
0A"
1{
1u
1v
bz0011 4
02"
03"
1l
1m
1x
05"
1o
1r
0/"
1i
1V"
1W"
bz0110 5
0_"
0`"
bz1100 6
1Z
1[
1Y"
0b"
1]
1R"
0["
1W
b1000 2
b0 1
bz1000 7
b11 ?
b11111101 #
b1101 &
b1101 +
b11111111111111111111111111111101 (
b101 )
#180
1-
b0 !
b0 9
b10000 :
b10000 8
bz0010 4
0~
0!"
0#"
0{
bz0100 5
0l
0m
0o
0i
bz1000 6
0Z
0[
0]
0W
bz0000 7
b10 ?
b11111110 #
b1110 &
b1110 +
b11111111111111111111111111111110 (
b110 )
#210
0,
0@
1-
bz0000 3
0;"
0<"
b1000 !
b1000 9
0>"
b1000 :
08"
b1000 8
0)"
0*"
bz0001 4
1~
1!"
0,"
1#"
0&"
1{
0u
0v
bz0010 5
1l
1m
0x
1o
0r
1i
0V"
0W"
bz0100 6
1Z
1[
0Y"
1]
0R"
1W
b0 2
bz1000 7
b1 ?
b11111111 #
b1111 &
b1111 +
b11111111111111111111111111111111 (
b111 )
#240
b0 !
b0 9
b0 8
bz0000 4
0~
0!"
0#"
0{
bz0000 5
0l
0m
0o
0i
bz0000 6
0Z
0[
0"
0]
0-
0W
0A
0@
bz0000 7
b0 :
1.
b0 ?
b0 #
b0 &
b0 +
b0 (
b1000 )
#270
1A
1@
b1000 !
b1000 9
b11111000 :
b1000 8
bz0001 4
1~
1!"
1#"
1{
bz0010 5
1l
1m
1o
1i
bz0100 6
1Z
1[
1]
1W
bz1000 7
b1 ?
b1 #
b1 &
b1 +
b1 (
b1001 )
#300
1"
1-
1A
1@
b0 !
b0 9
bz0001 3
1;"
1<"
b11110000 :
1>"
18"
b10000 8
1)"
1*"
bz0010 4
0~
0!"
1,"
0#"
1&"
0{
1u
1v
bz0100 5
0l
0m
1x
0o
1r
0i
1V"
1W"
bz1000 6
0Z
0[
1Y"
0]
1R"
0W
b1000 2
bz0000 7
b10 ?
b10 #
b10 &
b10 +
b10 (
b1010 )
#330
1,
0-
0A
b1000 !
b1000 9
b11101000 :
b11000 8
bz0011 4
1~
1!"
1#"
1{
bz0110 5
1l
1m
1o
1i
bz1100 6
1Z
1[
1]
1W
bz1000 7
b11 ?
b11 #
b11 &
b11 +
b11 (
b1011 )
#360
1-
b0 !
b0 9
0;"
0<"
b11100000 :
0>"
08"
b100000 8
0)"
0*"
bz0010 3
1D"
1E"
0~
0!"
0,"
1G"
0#"
0&"
1A"
0{
0u
0v
bz0100 4
12"
13"
0l
0m
0x
15"
0o
0r
1/"
0i
0V"
0W"
bz1000 5
1_"
1`"
bz0000 6
0Z
0[
0Y"
1b"
0]
0R"
1["
0W
b0 2
b1000 1
bz0000 7
b100 ?
b100 #
b100 &
b100 +
b100 (
b1100 )
#390
0-
b1000 !
b1000 9
b11011000 :
b101000 8
bz0101 4
1~
1!"
1#"
1{
bz1010 5
1l
1m
1o
1i
bz0100 6
1Z
1[
1]
1W
bz1000 7
b101 ?
b101 #
b101 &
b101 +
b101 (
b1101 )
#420
1-
b0 !
b0 9
bz0011 3
1;"
1<"
b11010000 :
1>"
18"
b110000 8
1)"
1*"
bz0110 4
0~
0!"
1,"
0#"
1&"
0{
1u
1v
bz1100 5
0l
0m
1x
0o
1r
0i
1V"
1W"
bz1000 6
0Z
0[
1Y"
0]
1R"
0W
b1000 2
bz0000 7
b110 ?
b110 #
b110 &
b110 +
b110 (
b1110 )
#450
0-
b1000 !
b1000 9
b11001000 :
b111000 8
bz0111 4
1~
1!"
1#"
1{
bz1110 5
1l
1m
1o
1i
bz1100 6
1Z
1[
1]
1W
bz1000 7
b111 ?
b111 #
b111 &
b111 +
b111 (
b1111 )
#480
1"
1,
0+"
1@
0M"
0N"
0&"
0P"
0-
0{
0u
0v
04"
1D"
1E"
0J"
bz0011 3
1;"
1<"
b1000 !
b1000 9
0l
0m
0x
1G"
0h"
0i"
1>"
0o
0r
0/"
1A"
0f"
18"
00"
b111000 8
0'"
0i
0V"
0W"
bz0000 5
0_"
0`"
12"
13"
01"
1)"
1*"
0("
bz0111 4
1~
1!"
b0 <
0}
bz0000 6
0Z
0[
0Y"
0b"
15"
06"
1,"
0-"
1#"
0$"
0]
0R"
0["
1."
1%"
1z
0W
b111000 :
b0 2
b0 1
b111 0
bz0000 7
0.
b111 B
b1000 ?
b11111000 #
b1000 &
b1000 +
b11111001 $
b1001 %
b1001 *
b11111111111111111111111111111001 '
b11111111111111111111111111111000 (
b10000 )
#510
1"
1/"
1_"
1`"
1,
1]"
1y
1n
1@
1t
1r
1j
0w
1V"
1W"
1b
1-
1s
1T"
1g
1D"
1E"
bz0011 3
1;"
1<"
b1110 =
1k
1Y
1`
1G"
1>"
0p
1\
1Q
1R
1A"
18"
1&"
0{
0i
1X
1O
12"
13"
1)"
1*"
bz0110 4
0~
0!"
1u
1v
0l
0m
bz1100 5
0c
0d
bz1010 6
0Z
0[
1P
b1110 >
1G
b1 !
b1 9
15"
1,"
0#"
0x
1o
0f
1]
1U
1L
b110001 :
0."
0%"
0z
1q
1h
1_
1V
1M
1D
1N
1E
b110001 8
b0 0
b111 1
b111 2
bz0111 7
b111 ?
b11111001 #
b1001 &
b1001 +
b11111111111111111111111111111001 (
b10001 )
#540
1,
1@
0;"
0<"
bz0010 3
1D"
1E"
0>"
1G"
0-
08"
1A"
0)"
0*"
12"
13"
0,"
15"
0&"
1/"
bz0101 4
1~
1!"
0u
0v
1w
1_"
1`"
1#"
1]"
1{
1t
1l
1m
1s
1x
0y
1k
0r
0n
0V"
0W"
1j
0o
1p
0T"
bz1010 5
0c
0d
b1110 =
1b
1i
0Y
0f
1g
1Z
1[
0\
1`
0X
0O
1Q
1R
0S
0P
bz0111 6
1H
1I
b0 >
0G
b1010 !
b1010 9
1T
0U
1K
0L
b101010 :
0N
0E
b101010 8
bz0000 7
b110 ?
b11111010 #
b1010 &
b1010 +
b11111111111111111111111111111010 (
b10010 )
#570
1"
1,
1@
1D"
1E"
1G"
1A"
bz0010 3
0;"
0<"
12"
13"
1-
0>"
15"
08"
1/"
0)"
0*"
1_"
1`"
0,"
1]"
bz0100 4
0~
0!"
0&"
1t
0#"
0u
0v
1w
0{
1s
bz1000 5
0l
0m
1n
b1110 =
1k
1o
0p
0i
bz0011 6
0Z
0[
b11 !
b11 9
0]
b100011 :
0V
0M
0D
1N
1E
b100011 8
b0 2
bz0111 7
b101 ?
b11111011 #
b1011 &
b1011 +
b11111111111111111111111111111011 (
b10011 )
