counter/6bitcounter.v
module dffe(q, d, clk, en, clr);
   //Inputs
   input d, clk, en, clr;
   //Internal wire
   wire clr;
   //Output
   output q;
   //Register
   reg q;
   //Intialize q to 0
   initial
   begin
       q = 1'b0;
   end

   //Set value of q on positive edge of the clock or clear
   always @(posedge clk or posedge clr) begin
       //If clear is high, set q to 0
       if (clr) begin
           q <= 1'b0;
       //If enable is high, set q to the value of d
       end else if (en) begin
           q <= d;
       end
   end
endmodule

module tff(t, clk, clr, q);
    input t, clk, clr;
    output q;

    wire d;
    xor(d, t, q);

    dffe dflipflop(q, d, clk, 1'b1, clr);
 
endmodule

module sixbitcount(clk, clr, q0, q1, q2, q3, q4, q5);
    input clk, clr;
    output q0, q1, q2, q3, q4, q5;

    wire w1, w2, w3, w4;

    tff t1(1'b1, clk, clr, q0);
    tff t2(q0, clk, clr, q1);
    and(w1, q0, q1);
    tff t3(w1, clk, clr, q2);

    and(w2, w1, q2);
    and(w3, q3, w2);
    and(w4, w3, q4);

    tff t4(w2, clk, clr, q3);
    tff t5(w3, clk, clr, q4);
    tff t6(w4, clk, clr, q5);
endmodule

counter/tb_tff.v
module tff_tb();  
reg clk;
reg reset;
reg t;
 
wire q;
wire qb;
 
tff tflipflop(t, clk, reset, q);

integer i;

initial begin
$monitor(clk,t,q,reset);
$dumpfile("tff.vcd");
$dumpvars(0, tff_tb);

reset = 0;
t = 1;
clk = 0;

for (i = 0; i < 10; i = i + 1) begin
clk = ~clk;
#10;
end

end
//always #25 clk = ~clk;
 
endmodule

counter/tff.vcd
$date
	Thu Feb 23 10:55:32 2023
$end
$version
	Icarus Verilog
$end
$timescale
	1s
$end
$scope module tff_tb $end
$var wire 1 ! q $end
$var reg 1 " clk $end
$var reg 1 # reset $end
$var reg 1 $ t $end
$var integer 32 % i [31:0] $end
$scope module tflipflop $end
$var wire 1 " clk $end
$var wire 1 # clr $end
$var wire 1 & d $end
$var wire 1 $ t $end
$var wire 1 ! q $end
$scope module dflipflop $end
$var wire 1 " clk $end
$var wire 1 # clr $end
$var wire 1 & d $end
$var wire 1 ' en $end
$var reg 1 ! q $end
$upscope $end
$upscope $end
$upscope $end
$enddefinitions $end
#0
$dumpvars
1'
0&
b0 %
1$
0#
1"
1!
$end
#10
0"
b1 %
#20
1&
0!
1"
b10 %
#30
0"
b11 %
#40
0&
1!
1"
b100 %
#50
0"
b101 %
#60
1&
0!
1"
b110 %
#70
0"
b111 %
#80
0&
1!
1"
b1000 %
#90
0"
b1001 %
#100
b1010 %
